[{"id":"45651365.d57f5c","type":"tab","label":"Lab3","disabled":false,"info":""},{"id":"57e01963.8be318","type":"inject","z":"45651365.d57f5c","name":"","topic":"","payload":"","payloadType":"date","repeat":"","crontab":"","once":false,"onceDelay":0.1,"x":100,"y":40,"wires":[["bbc6608.4a759a"]]},{"id":"bbc6608.4a759a","type":"oM2M-Application","z":"45651365.d57f5c","xSCL":"65ee47fa.e0ea48","xA":"a0f40d3d.9c5fa","obixType":"Demo","obixCategory":"GWApp","obixLocation":"NCKU","obixAnnounce":true,"x":250,"y":40,"wires":[["39136391.95814c"]]},{"id":"39136391.95814c","type":"http request","z":"45651365.d57f5c","name":"","method":"POST","ret":"txt","paytoqs":false,"url":"","tls":"","persist":false,"proxy":"","authType":"basic","x":410,"y":40,"wires":[["72731589.a9bc9c"]]},{"id":"72731589.a9bc9c","type":"debug","z":"45651365.d57f5c","name":"","active":true,"tosidebar":true,"console":false,"tostatus":false,"complete":"statusCode","targetType":"msg","x":580,"y":40,"wires":[]},{"id":"f3269f7d.11bef","type":"inject","z":"45651365.d57f5c","name":"","topic":"","payload":"","payloadType":"date","repeat":"","crontab":"","once":false,"onceDelay":0.1,"x":100,"y":100,"wires":[["926a8763.04cae8"]]},{"id":"c2a5ff40.9a1b9","type":"http request","z":"45651365.d57f5c","name":"","method":"POST","ret":"txt","paytoqs":false,"url":"","tls":"","persist":false,"proxy":"","authType":"basic","x":470,"y":100,"wires":[["6df9367e.75a8f8"]]},{"id":"6df9367e.75a8f8","type":"debug","z":"45651365.d57f5c","name":"","active":true,"tosidebar":true,"console":false,"tostatus":false,"complete":"statusCode","targetType":"msg","x":640,"y":100,"wires":[]},{"id":"25d98a80.a3dbd6","type":"inject","z":"45651365.d57f5c","name":"","topic":"","payload":"","payloadType":"date","repeat":"","crontab":"","once":false,"onceDelay":0.1,"x":100,"y":200,"wires":[["ee631e3d.fdddf"]]},{"id":"5f236004.d71df","type":"http request","z":"45651365.d57f5c","name":"","method":"POST","ret":"txt","paytoqs":false,"url":"","tls":"","persist":false,"proxy":"","authType":"basic","x":430,"y":200,"wires":[["5c3de44.fccfe1c"]]},{"id":"5c3de44.fccfe1c","type":"debug","z":"45651365.d57f5c","name":"","active":true,"tosidebar":true,"console":false,"tostatus":false,"complete":"statusCode","targetType":"msg","x":600,"y":200,"wires":[]},{"id":"a039cdf6.1283b","type":"inject","z":"45651365.d57f5c","name":"","topic":"","payload":"","payloadType":"date","repeat":"","crontab":"","once":false,"onceDelay":0.1,"x":100,"y":140,"wires":[["a831f763.5dc9c8"]]},{"id":"9296c9f5.367658","type":"http request","z":"45651365.d57f5c","name":"","method":"POST","ret":"txt","paytoqs":false,"url":"","tls":"","persist":false,"proxy":"","authType":"basic","x":510,"y":140,"wires":[["d4f2b31d.8acfc"]]},{"id":"d4f2b31d.8acfc","type":"debug","z":"45651365.d57f5c","name":"","active":true,"tosidebar":true,"console":false,"tostatus":false,"complete":"statusCode","targetType":"msg","x":680,"y":140,"wires":[]},{"id":"e204e613.c0c058","type":"inject","z":"45651365.d57f5c","name":"","topic":"","payload":"","payloadType":"date","repeat":"","crontab":"","once":false,"onceDelay":0.1,"x":100,"y":240,"wires":[["c086d7b2.fda918"]]},{"id":"acd24a64.bd12b8","type":"http request","z":"45651365.d57f5c","name":"","method":"POST","ret":"txt","paytoqs":false,"url":"","tls":"","persist":false,"proxy":"","authType":"basic","x":610,"y":240,"wires":[["4ba2964e.0e0588"]]},{"id":"4ba2964e.0e0588","type":"debug","z":"45651365.d57f5c","name":"","active":true,"tosidebar":true,"console":false,"tostatus":false,"complete":"statusCode","targetType":"msg","x":780,"y":240,"wires":[]},{"id":"c086d7b2.fda918","type":"function","z":"45651365.d57f5c","name":"MyDATA","func":"var data = { \n    type:'string', \n    unit:'testdata', \n    data: 'Hello World!' \n}; \nmsg.payload= JSON.stringify(data); \nreturn msg;","outputs":1,"noerr":0,"x":240,"y":240,"wires":[["b5f5e7e7.986568"]]},{"id":"a831f763.5dc9c8","type":"oM2M-Descriptor-ContentInstance","z":"45651365.d57f5c","xSCL":"65ee47fa.e0ea48","xA":"a0f40d3d.9c5fa","obixType":"","obixLocation":"","x":300,"y":140,"wires":[["9296c9f5.367658"]]},{"id":"ee631e3d.fdddf","type":"oM2M-Data-Container","z":"45651365.d57f5c","xSCL":"65ee47fa.e0ea48","xA":"a0f40d3d.9c5fa","maxNrOfInstances":"10","obixAnnounce":true,"x":260,"y":200,"wires":[["5f236004.d71df"]]},{"id":"b5f5e7e7.986568","type":"oM2M-Data-ContentInstance","z":"45651365.d57f5c","xSCL":"65ee47fa.e0ea48","xA":"a0f40d3d.9c5fa","obixCategory":"","x":420,"y":240,"wires":[["acd24a64.bd12b8"]]},{"id":"926a8763.04cae8","type":"oM2M-Descriptor-Container","z":"45651365.d57f5c","xSCL":"65ee47fa.e0ea48","xA":"a0f40d3d.9c5fa","x":280,"y":100,"wires":[["c2a5ff40.9a1b9"]]},{"id":"10af4f45.d5e311","type":"http request","z":"45651365.d57f5c","name":"","method":"POST","ret":"txt","paytoqs":false,"url":"","tls":"","persist":false,"proxy":"","authType":"basic","x":630,"y":300,"wires":[["96f32ae4.d6b498"]]},{"id":"e6b36a42.55cdf8","type":"function","z":"45651365.d57f5c","name":"Input Data","func":"var data = {\n    type:'string', \n    unit:'fakedata', \n    data: msg.payload.name \n}; \nmsg.payload = JSON.stringify(data); \nreturn msg;","outputs":1,"noerr":0,"x":250,"y":300,"wires":[["a19bf6af.6db538"]]},{"id":"a19bf6af.6db538","type":"oM2M-Data-ContentInstance","z":"45651365.d57f5c","xSCL":"65ee47fa.e0ea48","xA":"a0f40d3d.9c5fa","obixCategory":"","x":440,"y":300,"wires":[["10af4f45.d5e311"]]},{"id":"b22ffdea.5c557","type":"http in","z":"45651365.d57f5c","name":"Post Sensor Data","url":"/sensorData","method":"post","upload":false,"swaggerDoc":"","x":80,"y":300,"wires":[["e6b36a42.55cdf8","69f572.6953ba9"]]},{"id":"96f32ae4.d6b498","type":"debug","z":"45651365.d57f5c","name":"","active":true,"tosidebar":true,"console":false,"tostatus":false,"complete":"payload","targetType":"msg","x":790,"y":300,"wires":[]},{"id":"69f572.6953ba9","type":"http response","z":"45651365.d57f5c","name":"","statusCode":"","headers":{},"x":270,"y":360,"wires":[]},{"id":"65ee47fa.e0ea48","type":"xSCL","z":"","sclId":"gscl","host":"localhost","port":"8181","baseUrl":"/om2m/"},{"id":"a0f40d3d.9c5fa","type":"xA","z":"","appId":"MY_SENSOR","contactUrl":"localhost:1880"}]